azure/mgmt/datalake/__init__.py
azure_mgmt_datalake_nspkg-3.0.0.dist-info/METADATA
azure_mgmt_datalake_nspkg-3.0.0.dist-info/RECORD
azure_mgmt_datalake_nspkg-3.0.0.dist-info/WHEEL
azure_mgmt_datalake_nspkg-3.0.0.dist-info/top_level.txt
