Metadata-Version: 2.1
Name: azure-mgmt-datalake-nspkg
Version: 3.0.0
Summary: Microsoft Azure Data Lake Management Namespace Package [Internal]
Home-page: https://github.com/Azure/azure-sdk-for-python
Author: Microsoft Corporation
Author-email: azpysdkhelp@microsoft.com
License: MIT License
Platform: UNKNOWN
Classifier: Development Status :: 5 - Production/Stable
Classifier: Programming Language :: Python
Classifier: Programming Language :: Python :: 2
Classifier: Programming Language :: Python :: 2.7
Classifier: License :: OSI Approved :: MIT License
Requires-Python: <3
Requires-Dist: azure-mgmt-nspkg (>=3.0.0)
